mojimoji.cpython-312-i386-linux-gnu.so
mojimoji-0.0.13.dist-info/WHEEL
mojimoji-0.0.13.dist-info/top_level.txt
mojimoji-0.0.13.dist-info/LICENSE
mojimoji-0.0.13.dist-info/RECORD
mojimoji-0.0.13.dist-info/METADATA
mojimoji/py.typed
mojimoji/__init__.pyi
