Metadata-Version: 2.1
Name: mojimoji
Version: 0.0.13
Summary: A fast converter between Japanese hankaku and zenkaku characters
Home-page: http://github.com/studio-ousia/mojimoji
Author: Studio Ousia
Author-email: ikuya@ousia.jp
Keywords: japanese
Classifier: Development Status :: 4 - Beta
Classifier: Intended Audience :: Developers
Classifier: Natural Language :: Japanese
Classifier: License :: OSI Approved :: Apache Software License
Classifier: Programming Language :: Python
Classifier: Programming Language :: Python :: 3
Classifier: Programming Language :: Python :: 3.7
Classifier: Programming Language :: Python :: 3.8
Classifier: Programming Language :: Python :: 3.9
Classifier: Programming Language :: Python :: 3.10
Classifier: Programming Language :: Python :: 3.11
Classifier: Programming Language :: Python :: 3.12
Requires-Python: >=3.7
License-File: LICENSE
